pytokenbucket/__init__.py
pytokenbucket/tokenbucket.py
pytokenbucket-0.1.1.dist-info/AUTHORS.rst
pytokenbucket-0.1.1.dist-info/LICENSE
pytokenbucket-0.1.1.dist-info/METADATA
pytokenbucket-0.1.1.dist-info/WHEEL
pytokenbucket-0.1.1.dist-info/top_level.txt
pytokenbucket-0.1.1.dist-info/RECORD
